{"name":"mariadb","title":"MariaDB","description":"Community-developed MySQL fork with enhanced performance, security features, and storage engines. The default database backend for WordPress, BookStack, Nextcloud, and many more.","category":"database","target_stack":"core-infrastructure","icon":"🗄️","tags":["database","mysql","sql","mariadb","backend"],"variables":[{"name":"PORT_MARIADB","label":"Host Port","description":"Port to expose MariaDB on","default":"3306","required":false},{"name":"MARIADB_ROOT_PASSWORD","label":"Root Password","description":"Root password for MariaDB","default":"changeme","required":true}]}
